README.md
setup.py
hkh_dev_package.egg-info/PKG-INFO
hkh_dev_package.egg-info/SOURCES.txt
hkh_dev_package.egg-info/dependency_links.txt
hkh_dev_package.egg-info/entry_points.txt
hkh_dev_package.egg-info/namespace_packages.txt
hkh_dev_package.egg-info/requires.txt
hkh_dev_package.egg-info/top_level.txt
orangecontrib/__init__.py
orangecontrib/dev/__init__.py
orangecontrib/dev/widgets/Chatbot.py
orangecontrib/dev/widgets/DocumentEater.py
orangecontrib/dev/widgets/EmbeddingsCreation.py
orangecontrib/dev/widgets/LanguageModel.py
orangecontrib/dev/widgets/TextPreprocessing.py
orangecontrib/dev/widgets/__init__.py
orangecontrib/dev/widgets/goto.py
orangecontrib/dev/widgets/icons/Chatbot.svg
orangecontrib/dev/widgets/icons/DocumentEater.svg
orangecontrib/dev/widgets/icons/Embeddings.svg
orangecontrib/dev/widgets/icons/LanguageModel.svg
orangecontrib/dev/widgets/icons/TextPreprocessing.svg
orangecontrib/dev/widgets/icons/goto.png
orangecontrib/dev/widgets/kernel_function/Table_management.py
orangecontrib/dev/widgets/kernel_function/Utils_box.py
orangecontrib/dev/widgets/kernel_function/supp_moi_bis.tab
orangecontrib/dev/widgets/kernel_function/supp_moi_bis_permutation_tototo.tab
orangecontrib/dev/widgets/kernel_function/zoubida.dada
orangecontrib/dev/widgets/kernel_function/zoubida2.dada